LICENSE
MANIFEST.in
README.md
get_secret.py
setup.cfg
setup.py
get_secret.egg-info/PKG-INFO
get_secret.egg-info/SOURCES.txt
get_secret.egg-info/dependency_links.txt
get_secret.egg-info/top_level.txt