Metadata-Version: 1.1
Name: get-secret
Version: 0.0.2
Summary: Simple tool to fetch secrets for your application.
Home-page: https://github.com/tunedmystic/get-secret
Author: Sandeep Jadoonanan
Author-email: jsanweb@gmail.com
License: MIT
Download-URL: https://github.com/TunedMystic/get-secret/archive/v0.0.2.tar.gz
Keywords: secret,env,docker
Platform: UNKNOWN
Classifier: License :: OSI Approved :: MIT License
Classifier: Programming Language :: Python :: 2.7
Classifier: Programming Language :: Python :: 3.4
Classifier: Programming Language :: Python :: 3.5
Classifier: Programming Language :: Python :: 3.6
